reflex_llms/__init__.py
reflex_llms/containers.py
reflex_llms/models.py
reflex_llms/server.py
reflex_llms/settings.py
reflex_llms/utils.py
reflex_llms/configs/__init__.py
reflex_llms/configs/__pycache__/__init__.cpython-312.pyc
reflex_llms-0.2.0.data/data/requirements.txt
reflex_llms-0.2.0.dist-info/licenses/LICENSE
reflex_llms-0.2.0.dist-info/METADATA
reflex_llms-0.2.0.dist-info/WHEEL
reflex_llms-0.2.0.dist-info/top_level.txt
reflex_llms-0.2.0.dist-info/RECORD
