Metadata-Version: 2.4
Name: reflex-llms
Version: 0.2.0
Summary: Python package for autofallback to local LLMs if OpenAI API or Azure Endpoint is not available
Home-page: https://github.com/amadou-6e/docker-db.git
Author: Amadou Wolfgang Cisse
Author-email: amadou.6e@googlemail.com
Classifier: Programming Language :: Python :: 3
Classifier: Operating System :: OS Independent
Classifier: Topic :: Database
Classifier: Topic :: Software Development :: Libraries :: Python Modules
Requires-Python: >=3.6
License-File: LICENSE
Requires-Dist: docker
Requires-Dist: pytest
Requires-Dist: python-dotenv
Requires-Dist: openai
Requires-Dist: pydantic>=2.0.0
Requires-Dist: PyYAML
Requires-Dist: setuptools
Dynamic: author
Dynamic: author-email
Dynamic: classifier
Dynamic: description-content-type
Dynamic: home-page
Dynamic: license-file
Dynamic: requires-dist
Dynamic: requires-python
Dynamic: summary
